setup.py
HtmlProcessor/Grabber.py
HtmlProcessor/__init__.py
SimpleThreading/ThreadPool.py
SimpleThreading/ThreadingByFunction.py
SimpleThreading/__init__.py
ThreadDownloader8198.egg-info/PKG-INFO
ThreadDownloader8198.egg-info/SOURCES.txt
ThreadDownloader8198.egg-info/dependency_links.txt
ThreadDownloader8198.egg-info/requires.txt
ThreadDownloader8198.egg-info/top_level.txt